decouple-stubs/__init__.py
decouple-stubs/__init__.pyi
python_decouple_stubs-3.8.0.4.dist-info/LICENSE
python_decouple_stubs-3.8.0.4.dist-info/METADATA
python_decouple_stubs-3.8.0.4.dist-info/WHEEL
python_decouple_stubs-3.8.0.4.dist-info/entry_points.txt
python_decouple_stubs-3.8.0.4.dist-info/RECORD
