Metadata-Version: 2.1
Name: python-decouple-stubs
Version: 3.8.0.4
Summary: Stub file for the python-decouple package to enable static type checking
Home-page: https://github.com/tobievil/decouple-stubs
License: MIT
Author: TobiEvil
Author-email: 48364799+tobievil@users.noreply.github.com
Requires-Python: >=3.8,<4.0
Classifier: License :: OSI Approved :: MIT License
Classifier: Programming Language :: Python :: 3
Classifier: Programming Language :: Python :: 3.8
Classifier: Programming Language :: Python :: 3.9
Classifier: Programming Language :: Python :: 3.10
Classifier: Programming Language :: Python :: 3.11
Classifier: Programming Language :: Python :: 3.12
Classifier: Programming Language :: Python :: 3.13
Requires-Dist: python-decouple (==3.8)
Project-URL: Repository, https://github.com/tobievil/decouple-stubs
